wxpythoner.py
wxpythoner-0.0.2.dist-info/METADATA
wxpythoner-0.0.2.dist-info/WHEEL
wxpythoner-0.0.2.dist-info/entry_points.txt
wxpythoner-0.0.2.dist-info/top_level.txt
wxpythoner-0.0.2.dist-info/RECORD
